omlish/_check.cpython-313-darwin.so
omlish/collections/hamt/_hamt.cpython-313-darwin.so
omlish/lang/_asyncs.cpython-313-darwin.so
omlish/lang/imports/_capture.cpython-313-darwin.so
omlish/typedvalues/_collection.cpython-313-darwin.so
omlish_cext-0.0.0.dev516.dist-info/licenses/LICENSE
omlish_cext-0.0.0.dev516.dist-info/METADATA
omlish_cext-0.0.0.dev516.dist-info/WHEEL
omlish_cext-0.0.0.dev516.dist-info/top_level.txt
omlish_cext-0.0.0.dev516.dist-info/RECORD
